durationpy/__init__.py
durationpy/__init__.pyi
durationpy/duration.py
durationpy/py.typed
durationpy-0.10.dist-info/LICENSE
durationpy-0.10.dist-info/METADATA
durationpy-0.10.dist-info/WHEEL
durationpy-0.10.dist-info/top_level.txt
durationpy-0.10.dist-info/RECORD
